survival_data_handler/__init__.py
survival_data_handler/base.py
survival_data_handler/main.py
survival_data_handler/metric.py
survival_data_handler/plotting.py
survival_data_handler/utils.py
survival_data_handler-2024.4.10.dist-info/LICENSE
survival_data_handler-2024.4.10.dist-info/METADATA
survival_data_handler-2024.4.10.dist-info/WHEEL
survival_data_handler-2024.4.10.dist-info/top_level.txt
survival_data_handler-2024.4.10.dist-info/RECORD
