Metadata-Version: 2.1
Name: survival_data_handler
Version: 2024.4.10
Author-email: Vincent Laurent <vlaurent@eurobios.com>
License-File: LICENSE
Requires-Dist: matplotlib >=3
Requires-Dist: seaborn
Requires-Dist: numba
Requires-Dist: scipy
Requires-Dist: scikit-learn
Requires-Dist: pandas >2
Requires-Dist: lifelines
Requires-Dist: numpy
Requires-Dist: plotly
